{
    "drivers": {
        "00001": {
            "distance": "1",
            "name": "Moti Karpe",
            "phoneno": "9123456789",
            "routes": [
                [
                    13.09,
                    80.28,
                    "07:30",
                    "address 1"
                ],
                [
                    13.09,
                    80.28,
                    "08:30",
                    "address 2"
                ],
                [
                    13.153052,
                    80.247579,
                    "09:30",
                    "address 3"
                ],
                [
                    13.156959,
                    80.240986,
                    "10:30",
                    "address 4"
                ],
                [
                    13.170914,
                    80.21519,
                    "11:00",
                    "address 5"
                ],
                [
                    13.172109,
                    80.235598,
                    "11:30",
                    "address 6"
                ],
                [
                    13.165338,
                    80.243058,
                    "12:30",
                    "address 7"
                ],
                [
                    13.167007,
                    80.245859,
                    "13:30",
                    "address 8"
                ],
                [
                    13.173705,
                    80.257037,
                    "14:30",
                    "address 9"
                ],
                [
                    13.19283,
                    80.269619,
                    "15:30",
                    "address 10"
                ],
                [
                    13.198362,
                    80.272729,
                    "16:30",
                    "address 11"
                ],
                [
                    13.198362,
                    80.272729,
                    "17:30",
                    "address 12"
                ],
                [
                    13.184588,
                    80.308629,
                    "18:00",
                    "address 13"
                ],
                [
                    13.156614,
                    80.26875,
                    "18:30",
                    "address 14"
                ]
            ]
        },
        "00002": {
            "distance": "1",
            "name": "Naseer Lal Beharry",
            "phoneno": "0123456789",
            "routes": [
                [
                    13.100222,
                    80.165757,
                    "09:30",
                    "address 3"
                ],
                [
                    13.117873,
                    80.166199,
                    "10:30",
                    "address 4"
                ],
                [
                    13.117873,
                    80.166199,
                    "10:30",
                    "address 4"
                ]
            ]
        },
        "00003": {
            "distance": "1",
            "name": "Nurit",
            "phoneno": "0123456789",
            "routes": [
                [
                    13.09,
                    80.28,
                    "07:30",
                    "address 1"
                ],
                [
                    13.077503,
                    80.156623,
                    "07:30",
                    "address 1"
                ],
                [
                    13.141645,
                    80.104015,
                    "08:30",
                    "address 2"
                ],
                [
                    13.129786,
                    80.135400,
                    "09:30",
                    "address 3"
                ],
                [
                    13.101175,
                    80.151579,
                    "10:30",
                    "address 4"
                ]
            ]
        },
        "00004": {
            "distance": "1",
            "name": "Ayub",
            "phoneno": "0123456789",
            "routes": [
                [
                    13.09,
                    80.28,
                    "07:30",
                    "address 1"
                ],
                [
                    13.174303,
                    80.238985,
                    "07:30",
                    "address 1"
                ],
                [
                    13.156334,
                    80.224909,
                    "08:30",
                    "address 2"
                ],
                [
                    13.138054,
                    80.228643,
                    "09:30",
                    "address 3"
                ],
                [
                    13.116577,
                    80.262796,
                    "10:30",
                    "address 4"
                ]
            ]
        },
        "00005": {
            "distance": "1",
            "name": "Doron",
            "phoneno": "0123456789",
            "routes": [
                [
                    13.09,
                    80.28,
                    "07:30",
                    "address 1"
                ],
                [
                    13.096069,
                    80.275444,
                    "07:30",
                    "address 1"
                ],
                [
                    13.094825,
                    80.292566,
                    "08:30",
                    "address 2"
                ],
                [
                    13.115863,
                    80.292514,
                    "09:30",
                    "address 3"
                ],
                [
                    13.135411,
                    80.297190,
                    "10:30",
                    "address 4"
                ]
            ]
        },
        "00006": {
            "distance": "1",
            "name": "Idan",
            "phoneno": "0123456789",
            "routes": [
                [
                    13.09,
                    80.28,
                    "07:30",
                    "address 1"
                ],
                [
                    13.031988,
                    80.252498,
                    "07:30",
                    "address 1"
                ],
                [
                    13.018791,
                    80.262393,
                    "08:30",
                    "address 2"
                ],
                [
                    13.026903,
                    80.275483,
                    "09:30",
                    "address 3"
                ],
                [
                    13.043292,
                    80.275826,
                    "10:30",
                    "address 4"
                ]
            ]
        }
    },
    "status": true,
    "time_to_process": 2123213
}